delphai_fastapi/__init__.py
delphai_fastapi/app.py
delphai_fastapi/authorization.py
delphai_fastapi/companies/__init__.py
delphai_fastapi/companies/models.py
delphai_fastapi/decorators.py
delphai_fastapi/financials/__init__.py
delphai_fastapi/financials/models.py
delphai_fastapi/funding_rounds/__init__.py
delphai_fastapi/funding_rounds/models.py
delphai_fastapi/instrumentation.py
delphai_fastapi/job_posts/__init__.py
delphai_fastapi/job_posts/models.py
delphai_fastapi/middleware.py
delphai_fastapi/models.py
delphai_fastapi/mongo.py
delphai_fastapi/news_articles/__init__.py
delphai_fastapi/news_articles/models.py
delphai_fastapi/people/__init__.py
delphai_fastapi/people/models.py
delphai_fastapi/projects/__init__.py
delphai_fastapi/projects/models.py
delphai_fastapi/proxy.py
delphai_fastapi/server.py
delphai_fastapi/types.py
delphai_fastapi-9.8.0.dist-info/METADATA
delphai_fastapi-9.8.0.dist-info/WHEEL
delphai_fastapi-9.8.0.dist-info/RECORD
