Metadata-Version: 2.1
Name: delphai-fastapi
Version: 9.8.0
Summary: Package for fastAPI models
Author: Berinike Tech
Author-email: berinike@delphai.com
Requires-Python: >=3.11,<4.0
Classifier: Programming Language :: Python :: 3
Classifier: Programming Language :: Python :: 3.11
Classifier: Programming Language :: Python :: 3.12
Requires-Dist: fastapi (>=0.118,<1)
Requires-Dist: httpx (>=0.24)
Requires-Dist: hypercorn (>=0.17.3,<0.18.0)
Requires-Dist: prometheus-fastapi-instrumentator (>=6.1.0,<8)
Requires-Dist: pydantic (>=2.2,<3.0)
Requires-Dist: pymongo (>3)
Requires-Dist: python-jose (>=3.3,<4.0)
